rns_status_page/static/css/style.css
rns_status_page/static/favicon.png
rns_status_page/static/og.png
rns_status_page/static/vendor/htmx.min.js
rns_status_page/status_page.py
rns_status_page/templates/index.html
rns_status_page-1.5.0.dist-info/METADATA
rns_status_page-1.5.0.dist-info/WHEEL
rns_status_page-1.5.0.dist-info/entry_points.txt
rns_status_page-1.5.0.dist-info/licenses/LICENSE
rns_status_page-1.5.0.dist-info/RECORD
