Metadata-Version: 2.4
Name: rns-status-page
Version: 1.5.0
Summary: A Flask web server to display Reticulum network status.
License: MIT
License-File: LICENSE
Author: Ivan
Author-email: rns@quad4.io
Requires-Python: >=3.13,<4.0
Classifier: License :: OSI Approved :: MIT License
Classifier: Operating System :: OS Independent
Classifier: Programming Language :: Python :: 3
Classifier: Programming Language :: Python :: 3.13
Classifier: Programming Language :: Python :: 3.14
Requires-Dist: bleach (>=6.2.0,<7.0.0)
Requires-Dist: flask (==3.1.1)
Requires-Dist: flask-cors (>=6.0.1,<7.0.0)
Requires-Dist: flask-limiter (==3.12)
Requires-Dist: flask-talisman (==1.1.0)
Requires-Dist: gunicorn (==23.0.0)
Requires-Dist: python-dotenv (==1.1.0)
Requires-Dist: rns (==1.0.0)
Requires-Dist: werkzeug (>=3.1.3,<4.0.0)
Project-URL: Homepage, https://github.com/Sudo-Ivan/rns-status-page
Project-URL: Repository, https://github.com/Sudo-Ivan/rns-status-page
